dockertest/__init__.py
dockertest/base.py
dockertest/servicetest.py
dockertest-1.0.6.dist-info/DESCRIPTION.rst
dockertest-1.0.6.dist-info/METADATA
dockertest-1.0.6.dist-info/RECORD
dockertest-1.0.6.dist-info/WHEEL
dockertest-1.0.6.dist-info/metadata.json
dockertest-1.0.6.dist-info/top_level.txt
